instatext/__init__.py
instatext/predict_model.py
instatext/train_model.py
instatext-0.0.2.dist-info/LICENSE
instatext-0.0.2.dist-info/METADATA
instatext-0.0.2.dist-info/WHEEL
instatext-0.0.2.dist-info/top_level.txt
instatext-0.0.2.dist-info/RECORD
