Metadata-Version: 2.1
Name: instatext
Version: 0.0.2
Summary: instatext is a package to train text classifiers instantly.
Home-page: https://github.com/banjtheman/instatext
Author: Banjo Obayomi
Author-email: banjtheman@gmail.com
License: UNKNOWN
Keywords: python,text classifier,fasttext,nlp,spacy
Platform: UNKNOWN
Classifier: Development Status :: 1 - Planning
Classifier: Intended Audience :: Developers
Classifier: Natural Language :: English
Classifier: Programming Language :: Python
Classifier: Programming Language :: Python :: 3
Classifier: Programming Language :: Python :: 3.6
Classifier: Programming Language :: Python :: 3.7
Classifier: Programming Language :: Python :: 3.8
Requires-Python: >3.6
